{
    "committee": {
        "members": {},
        "threshold": 0
    },
    "constitution": {
        "anchor": {
            "dataHash": "0000000000000000000000000000000000000000000000000000000000000000",
            "url": ""
        }
    },
    "currentPParams": {
        "collateralPercentage": 150,
        "committeeMaxTermLength": 200,
        "committeeMinSize": 0,
        "costModels": {
            "PlutusV1": [
                205665,
                812,
                1,
                1,
                1000,
                571,
                0,
                1,
                1000,
                24177,
                4,
                1,
                1000,
                32,
                117366,
                10475,
                4,
                23000,
                100,
                23000,
                100,
                23000,
                100,
                23000,
                100,
                23000,
                100,
                23000,
                100,
                100,
                100,
                23000,
                100,
                19537,
                32,
                175354,
                32,
                46417,
                4,
                221973,
                511,
                0,
                1,
                89141,
                32,
                497525,
                14068,
                4,
                2,
                196500,
                453240,
                220,
                0,
                1,
                1,
                1000,
                28662,
                4,
                2,
                245000,
                216773,
                62,
                1,
                1060367,
                12586,
                1,
                208512,
                421,
                1,
                187000,
                1000,
                52998,
                1,
                80436,
                32,
                43249,
                32,
                1000,
                32,
                80556,
                1,
                57667,
                4,
                1000,
                10,
                197145,
                156,
                1,
                197145,
                156,
                1,
                204924,
                473,
                1,
                208896,
                511,
                1,
                52467,
                32,
                64832,
                32,
                65493,
                32,
                22558,
                32,
                16563,
                32,
                76511,
                32,
                196500,
                453240,
                220,
                0,
                1,
                1,
                69522,
                11687,
                0,
                1,
                60091,
                32,
                196500,
                453240,
                220,
                0,
                1,
                1,
                196500,
                453240,
                220,
                0,
                1,
                1,
                806990,
                30482,
                4,
                1927926,
                82523,
                4,
                265318,
                0,
                4,
                0,
                85931,
                32,
                205665,
                812,
                1,
                1,
                41182,
                32,
                212342,
                32,
                31220,
                32,
                32696,
                32,
                43357,
                32,
                32247,
                32,
                38314,
                32,
                57996947,
                18975,
                10
            ],
            "PlutusV2": [
                205665,
                812,
                1,
                1,
                1000,
                571,
                0,
                1,
                1000,
                24177,
                4,
                1,
                1000,
                32,
                117366,
                10475,
                4,
                23000,
                100,
                23000,
                100,
                23000,
                100,
                23000,
                100,
                23000,
                100,
                23000,
                100,
                100,
                100,
                23000,
                100,
                19537,
                32,
                175354,
                32,
                46417,
                4,
                221973,
                511,
                0,
                1,
                89141,
                32,
                497525,
                14068,
                4,
                2,
                196500,
                453240,
                220,
                0,
                1,
                1,
                1000,
                28662,
                4,
                2,
                245000,
                216773,
                62,
                1,
                1060367,
                12586,
                1,
                208512,
                421,
                1,
                187000,
                1000,
                52998,
                1,
                80436,
                32,
                43249,
                32,
                1000,
                32,
                80556,
                1,
                57667,
                4,
                1000,
                10,
                197145,
                156,
                1,
                197145,
                156,
                1,
                204924,
                473,
                1,
                208896,
                511,
                1,
                52467,
                32,
                64832,
                32,
                65493,
                32,
                22558,
                32,
                16563,
                32,
                76511,
                32,
                196500,
                453240,
                220,
                0,
                1,
                1,
                69522,
                11687,
                0,
                1,
                60091,
                32,
                196500,
                453240,
                220,
                0,
                1,
                1,
                196500,
                453240,
                220,
                0,
                1,
                1,
                1159724,
                392670,
                0,
                2,
                806990,
                30482,
                4,
                1927926,
                82523,
                4,
                265318,
                0,
                4,
                0,
                85931,
                32,
                205665,
                812,
                1,
                1,
                41182,
                32,
                212342,
                32,
                31220,
                32,
                32696,
                32,
                43357,
                32,
                32247,
                32,
                38314,
                32,
                35892428,
                10,
                9462713,
                1021,
                10,
                38887044,
                32947,
                10
            ],
            "PlutusV3": [
                0,
                0,
                0,
                0,
                0,
                0,
                0,
                0,
                0,
                0,
                0,
                0,
                0,
                0,
                0,
                0,
                0,
                0,
                0,
                0,
                0,
                0,
                0,
                0,
                0,
                0,
                0,
                0,
                0,
                0,
                0,
                0,
                0,
                0,
                0,
                0,
                0,
                0,
                0,
                0,
                0,
                0,
                0,
                0,
                0,
                0,
                0,
                0,
                0,
                0,
                0,
                0,
                0,
                0,
                0,
                0,
                0,
                0,
                0,
                0,
                0,
                0,
                0,
                0,
                0,
                0,
                0,
                0,
                0,
                0,
                0,
                0,
                0,
                0,
                0,
                0,
                0,
                0,
                0,
                0,
                0,
                0,
                0,
                0,
                0,
                0,
                0,
                0,
                0,
                0,
                0,
                0,
                0,
                0,
                0,
                0,
                0,
                0,
                0,
                0,
                0,
                0,
                0,
                0,
                0,
                0,
                0,
                0,
                0,
                0,
                0,
                0,
                0,
                0,
                0,
                0,
                0,
                0,
                0,
                0,
                0,
                0,
                0,
                0,
                0,
                0,
                0,
                0,
                0,
                0,
                0,
                0,
                0,
                0,
                0,
                0,
                0,
                0,
                0,
                0,
                0,
                0,
                0,
                0,
                0,
                0,
                0,
                0,
                0,
                0,
                0,
                0,
                0,
                0,
                0,
                0,
                0,
                0,
                0,
                0,
                0,
                0,
                0,
                0,
                0,
                0,
                0,
                0,
                0,
                0,
                0,
                0,
                0,
                0,
                0,
                0,
                0,
                0,
                0,
                0,
                0,
                0,
                0,
                0,
                0,
                0,
                0,
                0,
                0,
                0,
                0,
                0,
                0,
                0,
                0,
                0,
                0,
                0,
                0,
                0,
                0,
                0,
                0,
                0,
                0,
                0,
                0,
                0,
                0,
                0,
                0,
                0,
                0,
                0,
                0,
                0,
                0,
                0,
                0,
                0,
                0,
                0,
                0,
                0,
                0,
                0,
                0,
                0,
                0,
                0,
                0
            ]
        },
        "dRepActivity": 100,
        "dRepDeposit": 1000000,
        "dRepVotingThresholds": {
            "committeeNoConfidence": 0.1,
            "committeeNormal": 0.1,
            "hardForkInitiation": 0.1,
            "motionNoConfidence": 0.1,
            "ppEconomicGroup": 0.1,
            "ppGovGroup": 0.1,
            "ppNetworkGroup": 0.1,
            "ppTechnicalGroup": 0.1,
            "treasuryWithdrawal": 0.1,
            "updateToConstitution": 0.1
        },
        "executionUnitPrices": {
            "priceMemory": 5.77e-2,
            "priceSteps": 7.21e-5
        },
        "govActionDeposit": 1000000,
        "govActionLifetime": 2,
        "maxBlockBodySize": 65536,
        "maxBlockExecutionUnits": {
            "memory": 62000000,
            "steps": 20000000000
        },
        "maxBlockHeaderSize": 1100,
        "maxCollateralInputs": 3,
        "maxTxExecutionUnits": {
            "memory": 140000000,
            "steps": 10000000000
        },
        "maxTxSize": 16384,
        "maxValueSize": 5000,
        "minFeeRefScriptCostPerByte": 0,
        "minPoolCost": 0,
        "monetaryExpansion": 0.1,
        "poolPledgeInfluence": 0,
        "poolRetireMaxEpoch": 18,
        "poolVotingThresholds": {
            "committeeNoConfidence": 0.1,
            "committeeNormal": 0.1,
            "hardForkInitiation": 0.1,
            "motionNoConfidence": 0.1,
            "ppSecurityGroup": 0.1
        },
        "protocolVersion": {
            "major": 10,
            "minor": 0
        },
        "stakeAddressDeposit": 0,
        "stakePoolDeposit": 0,
        "stakePoolTargetNum": 100,
        "treasuryCut": 0.1,
        "txFeeFixed": 0,
        "txFeePerByte": 1,
        "utxoCostPerByte": 4310
    },
    "futurePParams": {
        "contents": null,
        "tag": "PotentialPParamsUpdate"
    },
    "nextRatifyState": {
        "enactedGovActions": [],
        "expiredGovActions": [],
        "nextEnactState": {
            "committee": {
                "members": {},
                "threshold": 0
            },
            "constitution": {
                "anchor": {
                    "dataHash": "0000000000000000000000000000000000000000000000000000000000000000",
                    "url": ""
                }
            },
            "curPParams": {
                "collateralPercentage": 150,
                "committeeMaxTermLength": 200,
                "committeeMinSize": 0,
                "costModels": {
                    "PlutusV1": [
                        205665,
                        812,
                        1,
                        1,
                        1000,
                        571,
                        0,
                        1,
                        1000,
                        24177,
                        4,
                        1,
                        1000,
                        32,
                        117366,
                        10475,
                        4,
                        23000,
                        100,
                        23000,
                        100,
                        23000,
                        100,
                        23000,
                        100,
                        23000,
                        100,
                        23000,
                        100,
                        100,
                        100,
                        23000,
                        100,
                        19537,
                        32,
                        175354,
                        32,
                        46417,
                        4,
                        221973,
                        511,
                        0,
                        1,
                        89141,
                        32,
                        497525,
                        14068,
                        4,
                        2,
                        196500,
                        453240,
                        220,
                        0,
                        1,
                        1,
                        1000,
                        28662,
                        4,
                        2,
                        245000,
                        216773,
                        62,
                        1,
                        1060367,
                        12586,
                        1,
                        208512,
                        421,
                        1,
                        187000,
                        1000,
                        52998,
                        1,
                        80436,
                        32,
                        43249,
                        32,
                        1000,
                        32,
                        80556,
                        1,
                        57667,
                        4,
                        1000,
                        10,
                        197145,
                        156,
                        1,
                        197145,
                        156,
                        1,
                        204924,
                        473,
                        1,
                        208896,
                        511,
                        1,
                        52467,
                        32,
                        64832,
                        32,
                        65493,
                        32,
                        22558,
                        32,
                        16563,
                        32,
                        76511,
                        32,
                        196500,
                        453240,
                        220,
                        0,
                        1,
                        1,
                        69522,
                        11687,
                        0,
                        1,
                        60091,
                        32,
                        196500,
                        453240,
                        220,
                        0,
                        1,
                        1,
                        196500,
                        453240,
                        220,
                        0,
                        1,
                        1,
                        806990,
                        30482,
                        4,
                        1927926,
                        82523,
                        4,
                        265318,
                        0,
                        4,
                        0,
                        85931,
                        32,
                        205665,
                        812,
                        1,
                        1,
                        41182,
                        32,
                        212342,
                        32,
                        31220,
                        32,
                        32696,
                        32,
                        43357,
                        32,
                        32247,
                        32,
                        38314,
                        32,
                        57996947,
                        18975,
                        10
                    ],
                    "PlutusV2": [
                        205665,
                        812,
                        1,
                        1,
                        1000,
                        571,
                        0,
                        1,
                        1000,
                        24177,
                        4,
                        1,
                        1000,
                        32,
                        117366,
                        10475,
                        4,
                        23000,
                        100,
                        23000,
                        100,
                        23000,
                        100,
                        23000,
                        100,
                        23000,
                        100,
                        23000,
                        100,
                        100,
                        100,
                        23000,
                        100,
                        19537,
                        32,
                        175354,
                        32,
                        46417,
                        4,
                        221973,
                        511,
                        0,
                        1,
                        89141,
                        32,
                        497525,
                        14068,
                        4,
                        2,
                        196500,
                        453240,
                        220,
                        0,
                        1,
                        1,
                        1000,
                        28662,
                        4,
                        2,
                        245000,
                        216773,
                        62,
                        1,
                        1060367,
                        12586,
                        1,
                        208512,
                        421,
                        1,
                        187000,
                        1000,
                        52998,
                        1,
                        80436,
                        32,
                        43249,
                        32,
                        1000,
                        32,
                        80556,
                        1,
                        57667,
                        4,
                        1000,
                        10,
                        197145,
                        156,
                        1,
                        197145,
                        156,
                        1,
                        204924,
                        473,
                        1,
                        208896,
                        511,
                        1,
                        52467,
                        32,
                        64832,
                        32,
                        65493,
                        32,
                        22558,
                        32,
                        16563,
                        32,
                        76511,
                        32,
                        196500,
                        453240,
                        220,
                        0,
                        1,
                        1,
                        69522,
                        11687,
                        0,
                        1,
                        60091,
                        32,
                        196500,
                        453240,
                        220,
                        0,
                        1,
                        1,
                        196500,
                        453240,
                        220,
                        0,
                        1,
                        1,
                        1159724,
                        392670,
                        0,
                        2,
                        806990,
                        30482,
                        4,
                        1927926,
                        82523,
                        4,
                        265318,
                        0,
                        4,
                        0,
                        85931,
                        32,
                        205665,
                        812,
                        1,
                        1,
                        41182,
                        32,
                        212342,
                        32,
                        31220,
                        32,
                        32696,
                        32,
                        43357,
                        32,
                        32247,
                        32,
                        38314,
                        32,
                        35892428,
                        10,
                        9462713,
                        1021,
                        10,
                        38887044,
                        32947,
                        10
                    ],
                    "PlutusV3": [
                        0,
                        0,
                        0,
                        0,
                        0,
                        0,
                        0,
                        0,
                        0,
                        0,
                        0,
                        0,
                        0,
                        0,
                        0,
                        0,
                        0,
                        0,
                        0,
                        0,
                        0,
                        0,
                        0,
                        0,
                        0,
                        0,
                        0,
                        0,
                        0,
                        0,
                        0,
                        0,
                        0,
                        0,
                        0,
                        0,
                        0,
                        0,
                        0,
                        0,
                        0,
                        0,
                        0,
                        0,
                        0,
                        0,
                        0,
                        0,
                        0,
                        0,
                        0,
                        0,
                        0,
                        0,
                        0,
                        0,
                        0,
                        0,
                        0,
                        0,
                        0,
                        0,
                        0,
                        0,
                        0,
                        0,
                        0,
                        0,
                        0,
                        0,
                        0,
                        0,
                        0,
                        0,
                        0,
                        0,
                        0,
                        0,
                        0,
                        0,
                        0,
                        0,
                        0,
                        0,
                        0,
                        0,
                        0,
                        0,
                        0,
                        0,
                        0,
                        0,
                        0,
                        0,
                        0,
                        0,
                        0,
                        0,
                        0,
                        0,
                        0,
                        0,
                        0,
                        0,
                        0,
                        0,
                        0,
                        0,
                        0,
                        0,
                        0,
                        0,
                        0,
                        0,
                        0,
                        0,
                        0,
                        0,
                        0,
                        0,
                        0,
                        0,
                        0,
                        0,
                        0,
                        0,
                        0,
                        0,
                        0,
                        0,
                        0,
                        0,
                        0,
                        0,
                        0,
                        0,
                        0,
                        0,
                        0,
                        0,
                        0,
                        0,
                        0,
                        0,
                        0,
                        0,
                        0,
                        0,
                        0,
                        0,
                        0,
                        0,
                        0,
                        0,
                        0,
                        0,
                        0,
                        0,
                        0,
                        0,
                        0,
                        0,
                        0,
                        0,
                        0,
                        0,
                        0,
                        0,
                        0,
                        0,
                        0,
                        0,
                        0,
                        0,
                        0,
                        0,
                        0,
                        0,
                        0,
                        0,
                        0,
                        0,
                        0,
                        0,
                        0,
                        0,
                        0,
                        0,
                        0,
                        0,
                        0,
                        0,
                        0,
                        0,
                        0,
                        0,
                        0,
                        0,
                        0,
                        0,
                        0,
                        0,
                        0,
                        0,
                        0,
                        0,
                        0,
                        0,
                        0,
                        0,
                        0,
                        0,
                        0,
                        0,
                        0,
                        0,
                        0,
                        0,
                        0,
                        0,
                        0,
                        0,
                        0,
                        0,
                        0,
                        0,
                        0,
                        0,
                        0,
                        0,
                        0
                    ]
                },
                "dRepActivity": 100,
                "dRepDeposit": 1000000,
                "dRepVotingThresholds": {
                    "committeeNoConfidence": 0.1,
                    "committeeNormal": 0.1,
                    "hardForkInitiation": 0.1,
                    "motionNoConfidence": 0.1,
                    "ppEconomicGroup": 0.1,
                    "ppGovGroup": 0.1,
                    "ppNetworkGroup": 0.1,
                    "ppTechnicalGroup": 0.1,
                    "treasuryWithdrawal": 0.1,
                    "updateToConstitution": 0.1
                },
                "executionUnitPrices": {
                    "priceMemory": 5.77e-2,
                    "priceSteps": 7.21e-5
                },
                "govActionDeposit": 1000000,
                "govActionLifetime": 2,
                "maxBlockBodySize": 65536,
                "maxBlockExecutionUnits": {
                    "memory": 62000000,
                    "steps": 20000000000
                },
                "maxBlockHeaderSize": 1100,
                "maxCollateralInputs": 3,
                "maxTxExecutionUnits": {
                    "memory": 140000000,
                    "steps": 10000000000
                },
                "maxTxSize": 16384,
                "maxValueSize": 5000,
                "minFeeRefScriptCostPerByte": 0,
                "minPoolCost": 0,
                "monetaryExpansion": 0.1,
                "poolPledgeInfluence": 0,
                "poolRetireMaxEpoch": 18,
                "poolVotingThresholds": {
                    "committeeNoConfidence": 0.1,
                    "committeeNormal": 0.1,
                    "hardForkInitiation": 0.1,
                    "motionNoConfidence": 0.1,
                    "ppSecurityGroup": 0.1
                },
                "protocolVersion": {
                    "major": 10,
                    "minor": 0
                },
                "stakeAddressDeposit": 0,
                "stakePoolDeposit": 0,
                "stakePoolTargetNum": 100,
                "treasuryCut": 0.1,
                "txFeeFixed": 0,
                "txFeePerByte": 1,
                "utxoCostPerByte": 4310
            },
            "prevGovActionIds": {
                "Committee": null,
                "Constitution": null,
                "HardFork": null,
                "PParamUpdate": null
            },
            "prevPParams": {
                "collateralPercentage": 150,
                "committeeMaxTermLength": 200,
                "committeeMinSize": 0,
                "costModels": {
                    "PlutusV1": [
                        205665,
                        812,
                        1,
                        1,
                        1000,
                        571,
                        0,
                        1,
                        1000,
                        24177,
                        4,
                        1,
                        1000,
                        32,
                        117366,
                        10475,
                        4,
                        23000,
                        100,
                        23000,
                        100,
                        23000,
                        100,
                        23000,
                        100,
                        23000,
                        100,
                        23000,
                        100,
                        100,
                        100,
                        23000,
                        100,
                        19537,
                        32,
                        175354,
                        32,
                        46417,
                        4,
                        221973,
                        511,
                        0,
                        1,
                        89141,
                        32,
                        497525,
                        14068,
                        4,
                        2,
                        196500,
                        453240,
                        220,
                        0,
                        1,
                        1,
                        1000,
                        28662,
                        4,
                        2,
                        245000,
                        216773,
                        62,
                        1,
                        1060367,
                        12586,
                        1,
                        208512,
                        421,
                        1,
                        187000,
                        1000,
                        52998,
                        1,
                        80436,
                        32,
                        43249,
                        32,
                        1000,
                        32,
                        80556,
                        1,
                        57667,
                        4,
                        1000,
                        10,
                        197145,
                        156,
                        1,
                        197145,
                        156,
                        1,
                        204924,
                        473,
                        1,
                        208896,
                        511,
                        1,
                        52467,
                        32,
                        64832,
                        32,
                        65493,
                        32,
                        22558,
                        32,
                        16563,
                        32,
                        76511,
                        32,
                        196500,
                        453240,
                        220,
                        0,
                        1,
                        1,
                        69522,
                        11687,
                        0,
                        1,
                        60091,
                        32,
                        196500,
                        453240,
                        220,
                        0,
                        1,
                        1,
                        196500,
                        453240,
                        220,
                        0,
                        1,
                        1,
                        806990,
                        30482,
                        4,
                        1927926,
                        82523,
                        4,
                        265318,
                        0,
                        4,
                        0,
                        85931,
                        32,
                        205665,
                        812,
                        1,
                        1,
                        41182,
                        32,
                        212342,
                        32,
                        31220,
                        32,
                        32696,
                        32,
                        43357,
                        32,
                        32247,
                        32,
                        38314,
                        32,
                        57996947,
                        18975,
                        10
                    ],
                    "PlutusV2": [
                        205665,
                        812,
                        1,
                        1,
                        1000,
                        571,
                        0,
                        1,
                        1000,
                        24177,
                        4,
                        1,
                        1000,
                        32,
                        117366,
                        10475,
                        4,
                        23000,
                        100,
                        23000,
                        100,
                        23000,
                        100,
                        23000,
                        100,
                        23000,
                        100,
                        23000,
                        100,
                        100,
                        100,
                        23000,
                        100,
                        19537,
                        32,
                        175354,
                        32,
                        46417,
                        4,
                        221973,
                        511,
                        0,
                        1,
                        89141,
                        32,
                        497525,
                        14068,
                        4,
                        2,
                        196500,
                        453240,
                        220,
                        0,
                        1,
                        1,
                        1000,
                        28662,
                        4,
                        2,
                        245000,
                        216773,
                        62,
                        1,
                        1060367,
                        12586,
                        1,
                        208512,
                        421,
                        1,
                        187000,
                        1000,
                        52998,
                        1,
                        80436,
                        32,
                        43249,
                        32,
                        1000,
                        32,
                        80556,
                        1,
                        57667,
                        4,
                        1000,
                        10,
                        197145,
                        156,
                        1,
                        197145,
                        156,
                        1,
                        204924,
                        473,
                        1,
                        208896,
                        511,
                        1,
                        52467,
                        32,
                        64832,
                        32,
                        65493,
                        32,
                        22558,
                        32,
                        16563,
                        32,
                        76511,
                        32,
                        196500,
                        453240,
                        220,
                        0,
                        1,
                        1,
                        69522,
                        11687,
                        0,
                        1,
                        60091,
                        32,
                        196500,
                        453240,
                        220,
                        0,
                        1,
                        1,
                        196500,
                        453240,
                        220,
                        0,
                        1,
                        1,
                        1159724,
                        392670,
                        0,
                        2,
                        806990,
                        30482,
                        4,
                        1927926,
                        82523,
                        4,
                        265318,
                        0,
                        4,
                        0,
                        85931,
                        32,
                        205665,
                        812,
                        1,
                        1,
                        41182,
                        32,
                        212342,
                        32,
                        31220,
                        32,
                        32696,
                        32,
                        43357,
                        32,
                        32247,
                        32,
                        38314,
                        32,
                        35892428,
                        10,
                        9462713,
                        1021,
                        10,
                        38887044,
                        32947,
                        10
                    ],
                    "PlutusV3": [
                        0,
                        0,
                        0,
                        0,
                        0,
                        0,
                        0,
                        0,
                        0,
                        0,
                        0,
                        0,
                        0,
                        0,
                        0,
                        0,
                        0,
                        0,
                        0,
                        0,
                        0,
                        0,
                        0,
                        0,
                        0,
                        0,
                        0,
                        0,
                        0,
                        0,
                        0,
                        0,
                        0,
                        0,
                        0,
                        0,
                        0,
                        0,
                        0,
                        0,
                        0,
                        0,
                        0,
                        0,
                        0,
                        0,
                        0,
                        0,
                        0,
                        0,
                        0,
                        0,
                        0,
                        0,
                        0,
                        0,
                        0,
                        0,
                        0,
                        0,
                        0,
                        0,
                        0,
                        0,
                        0,
                        0,
                        0,
                        0,
                        0,
                        0,
                        0,
                        0,
                        0,
                        0,
                        0,
                        0,
                        0,
                        0,
                        0,
                        0,
                        0,
                        0,
                        0,
                        0,
                        0,
                        0,
                        0,
                        0,
                        0,
                        0,
                        0,
                        0,
                        0,
                        0,
                        0,
                        0,
                        0,
                        0,
                        0,
                        0,
                        0,
                        0,
                        0,
                        0,
                        0,
                        0,
                        0,
                        0,
                        0,
                        0,
                        0,
                        0,
                        0,
                        0,
                        0,
                        0,
                        0,
                        0,
                        0,
                        0,
                        0,
                        0,
                        0,
                        0,
                        0,
                        0,
                        0,
                        0,
                        0,
                        0,
                        0,
                        0,
                        0,
                        0,
                        0,
                        0,
                        0,
                        0,
                        0,
                        0,
                        0,
                        0,
                        0,
                        0,
                        0,
                        0,
                        0,
                        0,
                        0,
                        0,
                        0,
                        0,
                        0,
                        0,
                        0,
                        0,
                        0,
                        0,
                        0,
                        0,
                        0,
                        0,
                        0,
                        0,
                        0,
                        0,
                        0,
                        0,
                        0,
                        0,
                        0,
                        0,
                        0,
                        0,
                        0,
                        0,
                        0,
                        0,
                        0,
                        0,
                        0,
                        0,
                        0,
                        0,
                        0,
                        0,
                        0,
                        0,
                        0,
                        0,
                        0,
                        0,
                        0,
                        0,
                        0,
                        0,
                        0,
                        0,
                        0,
                        0,
                        0,
                        0,
                        0,
                        0,
                        0,
                        0,
                        0,
                        0,
                        0,
                        0,
                        0,
                        0,
                        0,
                        0,
                        0,
                        0,
                        0,
                        0,
                        0,
                        0,
                        0,
                        0,
                        0,
                        0,
                        0,
                        0,
                        0,
                        0,
                        0,
                        0,
                        0
                    ]
                },
                "dRepActivity": 100,
                "dRepDeposit": 1000000,
                "dRepVotingThresholds": {
                    "committeeNoConfidence": 0.1,
                    "committeeNormal": 0.1,
                    "hardForkInitiation": 0.1,
                    "motionNoConfidence": 0.1,
                    "ppEconomicGroup": 0.1,
                    "ppGovGroup": 0.1,
                    "ppNetworkGroup": 0.1,
                    "ppTechnicalGroup": 0.1,
                    "treasuryWithdrawal": 0.1,
                    "updateToConstitution": 0.1
                },
                "executionUnitPrices": {
                    "priceMemory": 5.77e-2,
                    "priceSteps": 7.21e-5
                },
                "govActionDeposit": 1000000,
                "govActionLifetime": 2,
                "maxBlockBodySize": 65536,
                "maxBlockExecutionUnits": {
                    "memory": 62000000,
                    "steps": 20000000000
                },
                "maxBlockHeaderSize": 1100,
                "maxCollateralInputs": 3,
                "maxTxExecutionUnits": {
                    "memory": 140000000,
                    "steps": 10000000000
                },
                "maxTxSize": 16384,
                "maxValueSize": 5000,
                "minFeeRefScriptCostPerByte": 0,
                "minPoolCost": 0,
                "monetaryExpansion": 0.1,
                "poolPledgeInfluence": 0,
                "poolRetireMaxEpoch": 18,
                "poolVotingThresholds": {
                    "committeeNoConfidence": 0.1,
                    "committeeNormal": 0.1,
                    "hardForkInitiation": 0.1,
                    "motionNoConfidence": 0.1,
                    "ppSecurityGroup": 0.1
                },
                "protocolVersion": {
                    "major": 10,
                    "minor": 0
                },
                "stakeAddressDeposit": 0,
                "stakePoolDeposit": 0,
                "stakePoolTargetNum": 100,
                "treasuryCut": 0.1,
                "txFeeFixed": 0,
                "txFeePerByte": 1,
                "utxoCostPerByte": 4310
            }
        },
        "ratificationDelayed": false
    },
    "previousPParams": {
        "collateralPercentage": 150,
        "committeeMaxTermLength": 200,
        "committeeMinSize": 0,
        "costModels": {
            "PlutusV1": [
                205665,
                812,
                1,
                1,
                1000,
                571,
                0,
                1,
                1000,
                24177,
                4,
                1,
                1000,
                32,
                117366,
                10475,
                4,
                23000,
                100,
                23000,
                100,
                23000,
                100,
                23000,
                100,
                23000,
                100,
                23000,
                100,
                100,
                100,
                23000,
                100,
                19537,
                32,
                175354,
                32,
                46417,
                4,
                221973,
                511,
                0,
                1,
                89141,
                32,
                497525,
                14068,
                4,
                2,
                196500,
                453240,
                220,
                0,
                1,
                1,
                1000,
                28662,
                4,
                2,
                245000,
                216773,
                62,
                1,
                1060367,
                12586,
                1,
                208512,
                421,
                1,
                187000,
                1000,
                52998,
                1,
                80436,
                32,
                43249,
                32,
                1000,
                32,
                80556,
                1,
                57667,
                4,
                1000,
                10,
                197145,
                156,
                1,
                197145,
                156,
                1,
                204924,
                473,
                1,
                208896,
                511,
                1,
                52467,
                32,
                64832,
                32,
                65493,
                32,
                22558,
                32,
                16563,
                32,
                76511,
                32,
                196500,
                453240,
                220,
                0,
                1,
                1,
                69522,
                11687,
                0,
                1,
                60091,
                32,
                196500,
                453240,
                220,
                0,
                1,
                1,
                196500,
                453240,
                220,
                0,
                1,
                1,
                806990,
                30482,
                4,
                1927926,
                82523,
                4,
                265318,
                0,
                4,
                0,
                85931,
                32,
                205665,
                812,
                1,
                1,
                41182,
                32,
                212342,
                32,
                31220,
                32,
                32696,
                32,
                43357,
                32,
                32247,
                32,
                38314,
                32,
                57996947,
                18975,
                10
            ],
            "PlutusV2": [
                205665,
                812,
                1,
                1,
                1000,
                571,
                0,
                1,
                1000,
                24177,
                4,
                1,
                1000,
                32,
                117366,
                10475,
                4,
                23000,
                100,
                23000,
                100,
                23000,
                100,
                23000,
                100,
                23000,
                100,
                23000,
                100,
                100,
                100,
                23000,
                100,
                19537,
                32,
                175354,
                32,
                46417,
                4,
                221973,
                511,
                0,
                1,
                89141,
                32,
                497525,
                14068,
                4,
                2,
                196500,
                453240,
                220,
                0,
                1,
                1,
                1000,
                28662,
                4,
                2,
                245000,
                216773,
                62,
                1,
                1060367,
                12586,
                1,
                208512,
                421,
                1,
                187000,
                1000,
                52998,
                1,
                80436,
                32,
                43249,
                32,
                1000,
                32,
                80556,
                1,
                57667,
                4,
                1000,
                10,
                197145,
                156,
                1,
                197145,
                156,
                1,
                204924,
                473,
                1,
                208896,
                511,
                1,
                52467,
                32,
                64832,
                32,
                65493,
                32,
                22558,
                32,
                16563,
                32,
                76511,
                32,
                196500,
                453240,
                220,
                0,
                1,
                1,
                69522,
                11687,
                0,
                1,
                60091,
                32,
                196500,
                453240,
                220,
                0,
                1,
                1,
                196500,
                453240,
                220,
                0,
                1,
                1,
                1159724,
                392670,
                0,
                2,
                806990,
                30482,
                4,
                1927926,
                82523,
                4,
                265318,
                0,
                4,
                0,
                85931,
                32,
                205665,
                812,
                1,
                1,
                41182,
                32,
                212342,
                32,
                31220,
                32,
                32696,
                32,
                43357,
                32,
                32247,
                32,
                38314,
                32,
                35892428,
                10,
                9462713,
                1021,
                10,
                38887044,
                32947,
                10
            ],
            "PlutusV3": [
                0,
                0,
                0,
                0,
                0,
                0,
                0,
                0,
                0,
                0,
                0,
                0,
                0,
                0,
                0,
                0,
                0,
                0,
                0,
                0,
                0,
                0,
                0,
                0,
                0,
                0,
                0,
                0,
                0,
                0,
                0,
                0,
                0,
                0,
                0,
                0,
                0,
                0,
                0,
                0,
                0,
                0,
                0,
                0,
                0,
                0,
                0,
                0,
                0,
                0,
                0,
                0,
                0,
                0,
                0,
                0,
                0,
                0,
                0,
                0,
                0,
                0,
                0,
                0,
                0,
                0,
                0,
                0,
                0,
                0,
                0,
                0,
                0,
                0,
                0,
                0,
                0,
                0,
                0,
                0,
                0,
                0,
                0,
                0,
                0,
                0,
                0,
                0,
                0,
                0,
                0,
                0,
                0,
                0,
                0,
                0,
                0,
                0,
                0,
                0,
                0,
                0,
                0,
                0,
                0,
                0,
                0,
                0,
                0,
                0,
                0,
                0,
                0,
                0,
                0,
                0,
                0,
                0,
                0,
                0,
                0,
                0,
                0,
                0,
                0,
                0,
                0,
                0,
                0,
                0,
                0,
                0,
                0,
                0,
                0,
                0,
                0,
                0,
                0,
                0,
                0,
                0,
                0,
                0,
                0,
                0,
                0,
                0,
                0,
                0,
                0,
                0,
                0,
                0,
                0,
                0,
                0,
                0,
                0,
                0,
                0,
                0,
                0,
                0,
                0,
                0,
                0,
                0,
                0,
                0,
                0,
                0,
                0,
                0,
                0,
                0,
                0,
                0,
                0,
                0,
                0,
                0,
                0,
                0,
                0,
                0,
                0,
                0,
                0,
                0,
                0,
                0,
                0,
                0,
                0,
                0,
                0,
                0,
                0,
                0,
                0,
                0,
                0,
                0,
                0,
                0,
                0,
                0,
                0,
                0,
                0,
                0,
                0,
                0,
                0,
                0,
                0,
                0,
                0,
                0,
                0,
                0,
                0,
                0,
                0,
                0,
                0,
                0,
                0,
                0,
                0
            ]
        },
        "dRepActivity": 100,
        "dRepDeposit": 1000000,
        "dRepVotingThresholds": {
            "committeeNoConfidence": 0.1,
            "committeeNormal": 0.1,
            "hardForkInitiation": 0.1,
            "motionNoConfidence": 0.1,
            "ppEconomicGroup": 0.1,
            "ppGovGroup": 0.1,
            "ppNetworkGroup": 0.1,
            "ppTechnicalGroup": 0.1,
            "treasuryWithdrawal": 0.1,
            "updateToConstitution": 0.1
        },
        "executionUnitPrices": {
            "priceMemory": 5.77e-2,
            "priceSteps": 7.21e-5
        },
        "govActionDeposit": 1000000,
        "govActionLifetime": 2,
        "maxBlockBodySize": 65536,
        "maxBlockExecutionUnits": {
            "memory": 62000000,
            "steps": 20000000000
        },
        "maxBlockHeaderSize": 1100,
        "maxCollateralInputs": 3,
        "maxTxExecutionUnits": {
            "memory": 140000000,
            "steps": 10000000000
        },
        "maxTxSize": 16384,
        "maxValueSize": 5000,
        "minFeeRefScriptCostPerByte": 0,
        "minPoolCost": 0,
        "monetaryExpansion": 0.1,
        "poolPledgeInfluence": 0,
        "poolRetireMaxEpoch": 18,
        "poolVotingThresholds": {
            "committeeNoConfidence": 0.1,
            "committeeNormal": 0.1,
            "hardForkInitiation": 0.1,
            "motionNoConfidence": 0.1,
            "ppSecurityGroup": 0.1
        },
        "protocolVersion": {
            "major": 10,
            "minor": 0
        },
        "stakeAddressDeposit": 0,
        "stakePoolDeposit": 0,
        "stakePoolTargetNum": 100,
        "treasuryCut": 0.1,
        "txFeeFixed": 0,
        "txFeePerByte": 1,
        "utxoCostPerByte": 4310
    },
    "proposals": [
        {
            "actionId": {
                "govActionIx": 0,
                "txId": "664c65c7f7b4d064e2f138ba00c1d3056f0088533af1d719ac3cfa8911f51db2"
            },
            "committeeVotes": {},
            "dRepVotes": {
                "keyHash-01ee7fcdccd6685b317041b561685a74d814ef374ad4c0982fe70ab0": "VoteNo",
                "keyHash-24ed59f2cfb5f26c5fff8f5abedb637a362450e9c73f2e7878a2732f": "VoteNo",
                "keyHash-6e443dc9d93ac4bdf27d38c2ae1af0f083c93b572b791a07441d88ef": "VoteNo",
                "keyHash-99b04f8b472bbc91969acc8cfb857ab6000041d48186fb73a66d2bc0": "VoteNo",
                "keyHash-c48f3c6d38b4ebf34abb748ede5e50b80b3694c465b1979b7b8606b3": "VoteNo",
                "keyHash-c812f635d6dcef76591442d800ff10fa040475f658cba1aba71491b9": "VoteNo"
            },
            "expiresAfter": 10,
            "proposalProcedure": {
                "anchor": {
                    "dataHash": "602b957525f761055141104c8eace264d2246a57a9d9e37e08685e2d568d0ed0",
                    "url": "https://example.com/no_confidence.txt"
                },
                "deposit": 1000000,
                "govAction": {
                    "contents": null,
                    "tag": "NoConfidence"
                },
                "returnAddr": {
                    "credential": {
                        "keyHash": "179b068fed891a948b0de02f8045d5252958172d8d4c2093616914a1"
                    },
                    "network": "Testnet"
                }
            },
            "proposedIn": 8,
            "stakePoolVotes": {
                "1217f610c2721dc221cb958d058a22eed99c55608593d1480d576990": "VoteNo",
                "532633525f99798dec73d77773d7cf4cd8c800e46e20652f734515b3": "VoteNo",
                "7e86c8e821bba22e40154e718be904f65a93003ed0e142210fcc413d": "VoteNo",
                "a6a39b6fb10002d8d22d110b459764cb1016bbed83d612da6e3c396a": "VoteNo",
                "c595d2119704244106d02d72adb6b3e82dadf801b16319e571730fe5": "VoteNo",
                "e920dfee326614b3f93c63068cdba01a0dade0c23f7d593524ea820b": "VoteNo"
            }
        },
        {
            "actionId": {
                "govActionIx": 1,
                "txId": "664c65c7f7b4d064e2f138ba00c1d3056f0088533af1d719ac3cfa8911f51db2"
            },
            "committeeVotes": {},
            "dRepVotes": {},
            "expiresAfter": 10,
            "proposalProcedure": {
                "anchor": {
                    "dataHash": "602b957525f761055141104c8eace264d2246a57a9d9e37e08685e2d568d0ed0",
                    "url": "https://example.com/no_confidence.txt"
                },
                "deposit": 1000000,
                "govAction": {
                    "contents": null,
                    "tag": "NoConfidence"
                },
                "returnAddr": {
                    "credential": {
                        "keyHash": "381e3015c112592d0cad37ccc32429a9a3f5f0c30ca3bee5a9871a5b"
                    },
                    "network": "Testnet"
                }
            },
            "proposedIn": 8,
            "stakePoolVotes": {}
        },
        {
            "actionId": {
                "govActionIx": 2,
                "txId": "664c65c7f7b4d064e2f138ba00c1d3056f0088533af1d719ac3cfa8911f51db2"
            },
            "committeeVotes": {},
            "dRepVotes": {},
            "expiresAfter": 10,
            "proposalProcedure": {
                "anchor": {
                    "dataHash": "602b957525f761055141104c8eace264d2246a57a9d9e37e08685e2d568d0ed0",
                    "url": "https://example.com/no_confidence.txt"
                },
                "deposit": 1000000,
                "govAction": {
                    "contents": null,
                    "tag": "NoConfidence"
                },
                "returnAddr": {
                    "credential": {
                        "keyHash": "2b814f91fe6c6d051722bb64ab96e89fbce759ef8a52f104079ee8dd"
                    },
                    "network": "Testnet"
                }
            },
            "proposedIn": 8,
            "stakePoolVotes": {}
        },
        {
            "actionId": {
                "govActionIx": 3,
                "txId": "664c65c7f7b4d064e2f138ba00c1d3056f0088533af1d719ac3cfa8911f51db2"
            },
            "committeeVotes": {},
            "dRepVotes": {},
            "expiresAfter": 10,
            "proposalProcedure": {
                "anchor": {
                    "dataHash": "602b957525f761055141104c8eace264d2246a57a9d9e37e08685e2d568d0ed0",
                    "url": "https://example.com/no_confidence.txt"
                },
                "deposit": 1000000,
                "govAction": {
                    "contents": null,
                    "tag": "NoConfidence"
                },
                "returnAddr": {
                    "credential": {
                        "keyHash": "0b6c5eba27383951d4c04bd35892eaf8bcee94f2a8b8e90686115030"
                    },
                    "network": "Testnet"
                }
            },
            "proposedIn": 8,
            "stakePoolVotes": {}
        },
        {
            "actionId": {
                "govActionIx": 4,
                "txId": "664c65c7f7b4d064e2f138ba00c1d3056f0088533af1d719ac3cfa8911f51db2"
            },
            "committeeVotes": {},
            "dRepVotes": {},
            "expiresAfter": 10,
            "proposalProcedure": {
                "anchor": {
                    "dataHash": "602b957525f761055141104c8eace264d2246a57a9d9e37e08685e2d568d0ed0",
                    "url": "https://example.com/no_confidence.txt"
                },
                "deposit": 1000000,
                "govAction": {
                    "contents": null,
                    "tag": "NoConfidence"
                },
                "returnAddr": {
                    "credential": {
                        "keyHash": "829adef9661a56aa80021c94fefa7cd8537fc62ec2a2ec55c15a123a"
                    },
                    "network": "Testnet"
                }
            },
            "proposedIn": 8,
            "stakePoolVotes": {}
        }
    ]
}